{
  "team_slug": "cleveland-browns",
  "team_abbr": "CLE",
  "contract_count": 69,
  "contracts": [
    {
      "player_name": "Myles Garrett",
      "position": "ED",
      "age": 30,
      "base_salary_2025": 1255000,
      "cap_hit_2025": 22922120,
      "total_value": 68766360,
      "years": 3,
      "avg_salary": 22922120,
      "guaranteed": 4935725,
      "signing_bonus": 4308225
    },
    {
      "player_name": "Denzel Ward",
      "position": "CB",
      "age": 28,
      "base_salary_2025": 1255000,
      "cap_hit_2025": 14792211,
      "total_value": 44376633,
      "years": 3,
      "avg_salary": 14792211,
      "guaranteed": 4627500,
      "signing_bonus": 4000000
    },
    {
      "player_name": "Joel Bitonio",
      "position": "G",
      "age": 34,
      "base_salary_2025": 1255000,
      "cap_hit_2025": 11935615,
      "total_value": 35806845,
      "years": 3,
      "avg_salary": 11935615,
      "guaranteed": 1227500,
      "signing_bonus": 600000
    },
    {
      "player_name": "David Njoku",
      "position": "TE",
      "age": 29,
      "base_salary_2025": 1255000,
      "cap_hit_2025": 11436059,
      "total_value": 34308177,
      "years": 3,
      "avg_salary": 11436059,
      "guaranteed": 2920500,
      "signing_bonus": 2293000
    },
    {
      "player_name": "Jerry Jeudy",
      "position": "WR",
      "age": 26,
      "base_salary_2025": 1500000,
      "cap_hit_2025": 7979725,
      "total_value": 23939175,
      "years": 3,
      "avg_salary": 7979725,
      "guaranteed": 1952600,
      "signing_bonus": 1202600
    },
    {
      "player_name": "Mason Graham",
      "position": "DL",
      "age": 22,
      "base_salary_2025": 840000,
      "cap_hit_2025": 7435696,
      "total_value": 22307088,
      "years": 3,
      "avg_salary": 7435696,
      "guaranteed": 7011671,
      "signing_bonus": 6591671
    },
    {
      "player_name": "Grant Delpit",
      "position": "S",
      "age": 27,
      "base_salary_2025": 1170000,
      "cap_hit_2025": 5942465,
      "total_value": 17827395,
      "years": 3,
      "avg_salary": 5942465,
      "guaranteed": 1785000,
      "signing_bonus": 1200000
    },
    {
      "player_name": "Alex Wright",
      "position": "ED",
      "age": 25,
      "base_salary_2025": 2478668,
      "cap_hit_2025": 3490107,
      "total_value": 10470321,
      "years": 3,
      "avg_salary": 3490107,
      "guaranteed": 2172269,
      "signing_bonus": 932935
    },
    {
      "player_name": "Shelby Harris",
      "position": "DL",
      "age": 34,
      "base_salary_2025": 2000000,
      "cap_hit_2025": 3101315,
      "total_value": 9303945,
      "years": 3,
      "avg_salary": 3101315,
      "guaranteed": 1556000,
      "signing_bonus": 556000
    },
    {
      "player_name": "Cam Robinson",
      "position": "LT",
      "age": 30,
      "base_salary_2025": 1555556,
      "cap_hit_2025": 3011437,
      "total_value": 9034311,
      "years": 3,
      "avg_salary": 3011437,
      "guaranteed": 777778,
      "signing_bonus": 0
    },
    {
      "player_name": "Corey Bojorquez",
      "position": "P",
      "age": 29,
      "base_salary_2025": 2000000,
      "cap_hit_2025": 2442225,
      "total_value": 7326675,
      "years": 3,
      "avg_salary": 2442225,
      "guaranteed": 1437500,
      "signing_bonus": 437500
    },
    {
      "player_name": "Teven Jenkins",
      "position": "G",
      "age": 27,
      "base_salary_2025": 1170000,
      "cap_hit_2025": 2290000,
      "total_value": 6870000,
      "years": 3,
      "avg_salary": 2290000,
      "guaranteed": 885000,
      "signing_bonus": 300000
    },
    {
      "player_name": "Devin Bush",
      "position": "LB",
      "age": 27,
      "base_salary_2025": 1170000,
      "cap_hit_2025": 1795000,
      "total_value": 5385000,
      "years": 3,
      "avg_salary": 1795000,
      "guaranteed": 945000,
      "signing_bonus": 360000
    },
    {
      "player_name": "Cornelius Lucas",
      "position": "LT",
      "age": 34,
      "base_salary_2025": 1255000,
      "cap_hit_2025": 1662875,
      "total_value": 4988625,
      "years": 3,
      "avg_salary": 1662875,
      "guaranteed": 1027500,
      "signing_bonus": 400000
    },
    {
      "player_name": "Michael Hall",
      "position": "DL",
      "age": 22,
      "base_salary_2025": 1116356,
      "cap_hit_2025": 1614339,
      "total_value": 4843017,
      "years": 3,
      "avg_salary": 1614339,
      "guaranteed": 1048601,
      "signing_bonus": 490423
    },
    {
      "player_name": "Cedric Tillman",
      "position": "WR",
      "age": 25,
      "base_salary_2025": 1207542,
      "cap_hit_2025": 1538631,
      "total_value": 4615893,
      "years": 3,
      "avg_salary": 1538631,
      "guaranteed": 873855,
      "signing_bonus": 270084
    },
    {
      "player_name": "Tyson Campbell",
      "position": "CB",
      "age": 25,
      "base_salary_2025": 1083333,
      "cap_hit_2025": 1436274,
      "total_value": 4308822,
      "years": 3,
      "avg_salary": 1436274,
      "guaranteed": 541666,
      "signing_bonus": 0
    },
    {
      "player_name": "Rayshawn Jenkins",
      "position": "S",
      "age": 31,
      "base_salary_2025": 1255000,
      "cap_hit_2025": 1426595,
      "total_value": 4279785,
      "years": 3,
      "avg_salary": 1426595,
      "guaranteed": 795000,
      "signing_bonus": 167500
    },
    {
      "player_name": "Cam Thomas",
      "position": "ED",
      "age": 25,
      "base_salary_2025": 1406501,
      "cap_hit_2025": 1415006,
      "total_value": 4245018,
      "years": 3,
      "avg_salary": 1415006,
      "guaranteed": 703250,
      "signing_bonus": 0
    },
    {
      "player_name": "Zak Zinter",
      "position": "G",
      "age": 24,
      "base_salary_2025": 1000670,
      "cap_hit_2025": 1311855,
      "total_value": 3935565,
      "years": 3,
      "avg_salary": 1311855,
      "guaranteed": 748015,
      "signing_bonus": 247680
    },
    {
      "player_name": "Harold Fannin Jr.",
      "position": "TE",
      "age": 21,
      "base_salary_2025": 840000,
      "cap_hit_2025": 1230004,
      "total_value": 3690012,
      "years": 3,
      "avg_salary": 1230004,
      "guaranteed": 805979,
      "signing_bonus": 385979
    },
    {
      "player_name": "Isaiah McGuire",
      "position": "ED",
      "age": 24,
      "base_salary_2025": 1030000,
      "cap_hit_2025": 1216173,
      "total_value": 3648519,
      "years": 3,
      "avg_salary": 1216173,
      "guaranteed": 692983,
      "signing_bonus": 177983
    },
    {
      "player_name": "Jerome Baker",
      "position": "LB",
      "age": 29,
      "base_salary_2025": 1255000,
      "cap_hit_2025": 1203800,
      "total_value": 3611400,
      "years": 3,
      "avg_salary": 1203800,
      "guaranteed": 795000,
      "signing_bonus": 167500
    },
    {
      "player_name": "Dillon Gabriel",
      "position": "QB",
      "age": 25,
      "base_salary_2025": 840000,
      "cap_hit_2025": 1135761,
      "total_value": 3407283,
      "years": 3,
      "avg_salary": 1135761,
      "guaranteed": 712058,
      "signing_bonus": 292058
    },
    {
      "player_name": "Luke Wypler",
      "position": "C",
      "age": 24,
      "base_salary_2025": 1030000,
      "cap_hit_2025": 1083498,
      "total_value": 3250494,
      "years": 3,
      "avg_salary": 1083498,
      "guaranteed": 559993,
      "signing_bonus": 44993
    },
    {
      "player_name": "Dylan Sampson",
      "position": "RB",
      "age": 21,
      "base_salary_2025": 840000,
      "cap_hit_2025": 1076666,
      "total_value": 3229998,
      "years": 3,
      "avg_salary": 1076666,
      "guaranteed": 652641,
      "signing_bonus": 232641
    },
    {
      "player_name": "Mohamoud Diabate",
      "position": "LB",
      "age": 24,
      "base_salary_2025": 1030000,
      "cap_hit_2025": 1046524,
      "total_value": 3139572,
      "years": 3,
      "avg_salary": 1046524,
      "guaranteed": 523334,
      "signing_bonus": 8334
    },
    {
      "player_name": "Ronnie Hickman",
      "position": "S",
      "age": 24,
      "base_salary_2025": 1030000,
      "cap_hit_2025": 1045172,
      "total_value": 3135516,
      "years": 3,
      "avg_salary": 1045172,
      "guaranteed": 521667,
      "signing_bonus": 6667
    },
    {
      "player_name": "Blake Whiteheart",
      "position": "TE",
      "age": 25,
      "base_salary_2025": 1030000,
      "cap_hit_2025": 1038505,
      "total_value": 3115515,
      "years": 3,
      "avg_salary": 1038505,
      "guaranteed": 515000,
      "signing_bonus": 0
    },
    {
      "player_name": "Myles Harden",
      "position": "CB",
      "age": 24,
      "base_salary_2025": 960000,
      "cap_hit_2025": 996088,
      "total_value": 2988264,
      "years": 3,
      "avg_salary": 996088,
      "guaranteed": 507583,
      "signing_bonus": 27583
    },
    {
      "player_name": "Rex Sunahara",
      "position": "LS",
      "age": 29,
      "base_salary_2025": 960000,
      "cap_hit_2025": 968505,
      "total_value": 2905515,
      "years": 3,
      "avg_salary": 968505,
      "guaranteed": 480000,
      "signing_bonus": 0
    },
    {
      "player_name": "Shedeur Sanders",
      "position": "QB",
      "age": 23,
      "base_salary_2025": 840000,
      "cap_hit_2025": 955548,
      "total_value": 2866644,
      "years": 3,
      "avg_salary": 955548,
      "guaranteed": 531845,
      "signing_bonus": 111845
    },
    {
      "player_name": "Isaiah Bond",
      "position": "WR",
      "age": 21,
      "base_salary_2025": 840000,
      "cap_hit_2025": 857666,
      "total_value": 2572998,
      "years": 3,
      "avg_salary": 857666,
      "guaranteed": 437666,
      "signing_bonus": 17666
    },
    {
      "player_name": "Adin Huntington",
      "position": "DL",
      "age": 23,
      "base_salary_2025": 840000,
      "cap_hit_2025": 850691,
      "total_value": 2552073,
      "years": 3,
      "avg_salary": 850691,
      "guaranteed": 426666,
      "signing_bonus": 6666
    },
    {
      "player_name": "Easton Mascarenas-Arnold",
      "position": "LB",
      "age": 23,
      "base_salary_2025": 840000,
      "cap_hit_2025": 847358,
      "total_value": 2542074,
      "years": 3,
      "avg_salary": 847358,
      "guaranteed": 423333,
      "signing_bonus": 3333
    },
    {
      "player_name": "Donovan McMillon",
      "position": "S",
      "age": 23,
      "base_salary_2025": 840000,
      "cap_hit_2025": 847358,
      "total_value": 2542074,
      "years": 3,
      "avg_salary": 847358,
      "guaranteed": 423333,
      "signing_bonus": 3333
    },
    {
      "player_name": "Andre Szmyt",
      "position": "K",
      "age": 27,
      "base_salary_2025": 840000,
      "cap_hit_2025": 847245,
      "total_value": 2541735,
      "years": 3,
      "avg_salary": 847245,
      "guaranteed": 420000,
      "signing_bonus": 0
    },
    {
      "player_name": "KT Leveston",
      "position": "G",
      "age": 26,
      "base_salary_2025": 840000,
      "cap_hit_2025": 840000,
      "total_value": 2520000,
      "years": 3,
      "avg_salary": 840000,
      "guaranteed": 420000,
      "signing_bonus": 0
    },
    {
      "player_name": "Raheim Sanders",
      "position": "RB",
      "age": 23,
      "base_salary_2025": 840000,
      "cap_hit_2025": 840000,
      "total_value": 2520000,
      "years": 3,
      "avg_salary": 840000,
      "guaranteed": 420000,
      "signing_bonus": 0
    },
    {
      "player_name": "Malachi Corley",
      "position": "WR",
      "age": 23,
      "base_salary_2025": 960000,
      "cap_hit_2025": 746667,
      "total_value": 2240001,
      "years": 3,
      "avg_salary": 746667,
      "guaranteed": 480000,
      "signing_bonus": 0
    },
    {
      "player_name": "Gage Larvadain",
      "position": "WR",
      "age": 22,
      "base_salary_2025": 840000,
      "cap_hit_2025": 653333,
      "total_value": 1959999,
      "years": 3,
      "avg_salary": 653333,
      "guaranteed": 420000,
      "signing_bonus": 0
    },
    {
      "player_name": "Brenden Bates",
      "position": "TE",
      "age": 26,
      "base_salary_2025": 960000,
      "cap_hit_2025": 533330,
      "total_value": 1599990,
      "years": 3,
      "avg_salary": 533330,
      "guaranteed": 480000,
      "signing_bonus": 0
    },
    {
      "player_name": "D'Angelo Ross",
      "position": "CB",
      "age": 29,
      "base_salary_2025": 1100000,
      "cap_hit_2025": 427778,
      "total_value": 1283334,
      "years": 3,
      "avg_salary": 427778,
      "guaranteed": 550000,
      "signing_bonus": 0
    },
    {
      "player_name": "Sam Webb",
      "position": "CB",
      "age": 27,
      "base_salary_2025": 1100000,
      "cap_hit_2025": 427778,
      "total_value": 1283334,
      "years": 3,
      "avg_salary": 427778,
      "guaranteed": 550000,
      "signing_bonus": 0
    },
    {
      "player_name": "Sam Kamara",
      "position": "DL",
      "age": 28,
      "base_salary_2025": 1100000,
      "cap_hit_2025": 305556,
      "total_value": 916668,
      "years": 3,
      "avg_salary": 305556,
      "guaranteed": 550000,
      "signing_bonus": 0
    },
    {
      "player_name": "Tre Avery",
      "position": "S",
      "age": 28,
      "base_salary_2025": 1100000,
      "cap_hit_2025": 244444,
      "total_value": 733332,
      "years": 3,
      "avg_salary": 244444,
      "guaranteed": 550000,
      "signing_bonus": 0
    },
    {
      "player_name": "Trayveon Williams",
      "position": "RB",
      "age": 28,
      "base_salary_2025": 1170000,
      "cap_hit_2025": 228888,
      "total_value": 686664,
      "years": 3,
      "avg_salary": 228888,
      "guaranteed": 585000,
      "signing_bonus": 0
    },
    {
      "player_name": "Jeremiah Byers",
      "position": "T",
      "age": 24,
      "base_salary_2025": 840000,
      "cap_hit_2025": 186668,
      "total_value": 560004,
      "years": 3,
      "avg_salary": 186668,
      "guaranteed": 420000,
      "signing_bonus": 0
    },
    {
      "player_name": "Jamari Thrash",
      "position": "WR",
      "age": 25,
      "base_salary_2025": 960000,
      "cap_hit_2025": 160000,
      "total_value": 480000,
      "years": 3,
      "avg_salary": 160000,
      "guaranteed": 480000,
      "signing_bonus": 0
    },
    {
      "player_name": "Chris Edmonds",
      "position": "S",
      "age": 24,
      "base_salary_2025": 840000,
      "cap_hit_2025": 140000,
      "total_value": 420000,
      "years": 3,
      "avg_salary": 140000,
      "guaranteed": 420000,
      "signing_bonus": 0
    },
    {
      "player_name": "Kendrick Green",
      "position": "G",
      "age": 27,
      "base_salary_2025": 1170000,
      "cap_hit_2025": 130000,
      "total_value": 390000,
      "years": 3,
      "avg_salary": 130000,
      "guaranteed": 585000,
      "signing_bonus": 0
    },
    {
      "player_name": "Edefuan Ulofoshio",
      "position": "LB",
      "age": 25,
      "base_salary_2025": 960000,
      "cap_hit_2025": 53333,
      "total_value": 159999,
      "years": 3,
      "avg_salary": 53333,
      "guaranteed": 480000,
      "signing_bonus": 0
    },
    {
      "player_name": "Kingsley Eguakun",
      "position": "C",
      "age": 24,
      "base_salary_2025": 840000,
      "cap_hit_2025": 46667,
      "total_value": 140001,
      "years": 3,
      "avg_salary": 46667,
      "guaranteed": 420000,
      "signing_bonus": 0
    },
    {
      "player_name": "Wyatt Teller",
      "position": "G",
      "age": 31,
      "base_salary_2025": 1255000,
      "cap_hit_2025": 12446566,
      "total_value": 37339698,
      "years": 3,
      "avg_salary": 12446566,
      "guaranteed": 2753800,
      "signing_bonus": 2126300
    },
    {
      "player_name": "Ethan Pocic",
      "position": "C",
      "age": 30,
      "base_salary_2025": 5660000,
      "cap_hit_2025": 7772190,
      "total_value": 23316570,
      "years": 3,
      "avg_salary": 7772190,
      "guaranteed": 3814000,
      "signing_bonus": 984000
    },
    {
      "player_name": "Jack Conklin",
      "position": "RT",
      "age": 31,
      "base_salary_2025": 1255000,
      "cap_hit_2025": 5629818,
      "total_value": 16889454,
      "years": 3,
      "avg_salary": 5629818,
      "guaranteed": 1527500,
      "signing_bonus": 900000
    },
    {
      "player_name": "Maliek Collins",
      "position": "DL",
      "age": 30,
      "base_salary_2025": 1255000,
      "cap_hit_2025": 4204315,
      "total_value": 12612945,
      "years": 3,
      "avg_salary": 4204315,
      "guaranteed": 3556500,
      "signing_bonus": 2929000
    },
    {
      "player_name": "Martin Emerson",
      "position": "CB",
      "age": 25,
      "base_salary_2025": 3606000,
      "cap_hit_2025": 3954285,
      "total_value": 11862855,
      "years": 3,
      "avg_salary": 3954285,
      "guaranteed": 2092780,
      "signing_bonus": 289780
    },
    {
      "player_name": "Carson Schwesinger",
      "position": "LB",
      "age": 22,
      "base_salary_2025": 840000,
      "cap_hit_2025": 2149552,
      "total_value": 6448656,
      "years": 3,
      "avg_salary": 2149552,
      "guaranteed": 1725527,
      "signing_bonus": 1305527
    },
    {
      "player_name": "Quinshon Judkins",
      "position": "RB",
      "age": 22,
      "base_salary_2025": 840000,
      "cap_hit_2025": 2076815,
      "total_value": 6230445,
      "years": 3,
      "avg_salary": 2076815,
      "guaranteed": 1653112,
      "signing_bonus": 1233112
    },
    {
      "player_name": "Jerome Ford",
      "position": "RB",
      "age": 26,
      "base_salary_2025": 1750000,
      "cap_hit_2025": 1839042,
      "total_value": 5517126,
      "years": 3,
      "avg_salary": 1839042,
      "guaranteed": 955537,
      "signing_bonus": 80537
    },
    {
      "player_name": "Dawand Jones",
      "position": "LT",
      "age": 24,
      "base_salary_2025": 1030000,
      "cap_hit_2025": 1236588,
      "total_value": 3709764,
      "years": 3,
      "avg_salary": 1236588,
      "guaranteed": 713083,
      "signing_bonus": 198083
    },
    {
      "player_name": "Deandre Carter",
      "position": "WR",
      "age": 32,
      "base_salary_2025": 1255000,
      "cap_hit_2025": 1206005,
      "total_value": 3618015,
      "years": 3,
      "avg_salary": 1206005,
      "guaranteed": 795000,
      "signing_bonus": 167500
    },
    {
      "player_name": "Winston Reid",
      "position": "LB",
      "age": 26,
      "base_salary_2025": 960000,
      "cap_hit_2025": 968505,
      "total_value": 2905515,
      "years": 3,
      "avg_salary": 968505,
      "guaranteed": 480000,
      "signing_bonus": 0
    },
    {
      "player_name": "Nathaniel Watson",
      "position": "LB",
      "age": 25,
      "base_salary_2025": 515000,
      "cap_hit_2025": 523505,
      "total_value": 1570515,
      "years": 3,
      "avg_salary": 523505,
      "guaranteed": 257500,
      "signing_bonus": 0
    },
    {
      "player_name": "Anthony Kendall",
      "position": "CB",
      "age": 26,
      "base_salary_2025": 515000,
      "cap_hit_2025": 522245,
      "total_value": 1566735,
      "years": 3,
      "avg_salary": 522245,
      "guaranteed": 257500,
      "signing_bonus": 0
    },
    {
      "player_name": "Justin Osborne",
      "position": "C",
      "age": 25,
      "base_salary_2025": 490000,
      "cap_hit_2025": 498381,
      "total_value": 1495143,
      "years": 3,
      "avg_salary": 498381,
      "guaranteed": 250000,
      "signing_bonus": 5000
    },
    {
      "player_name": "Dom Jones",
      "position": "CB",
      "age": 25,
      "base_salary_2025": 840000,
      "cap_hit_2025": 470558,
      "total_value": 1411674,
      "years": 3,
      "avg_salary": 470558,
      "guaranteed": 420000,
      "signing_bonus": 0
    },
    {
      "player_name": "Julian Okwara",
      "position": "ED",
      "age": 28,
      "base_salary_2025": 396000,
      "cap_hit_2025": 396000,
      "total_value": 1188000,
      "years": 3,
      "avg_salary": 396000,
      "guaranteed": 198000,
      "signing_bonus": 0
    }
  ]
}